LICENSE.txt
README.txt
buildout.cfg
setup.py
bootstrap/bootstrap.py
src/GrokIMDB.egg-info/PKG-INFO
src/GrokIMDB.egg-info/SOURCES.txt
src/GrokIMDB.egg-info/dependency_links.txt
src/GrokIMDB.egg-info/entry_points.txt
src/GrokIMDB.egg-info/not-zip-safe
src/GrokIMDB.egg-info/requires.txt
src/GrokIMDB.egg-info/top_level.txt
src/grokimdb/README.txt
src/grokimdb/__init__.py
src/grokimdb/app.py
src/grokimdb/browser.txt
src/grokimdb/configure.zcml
src/grokimdb/ftesting.zcml
src/grokimdb/ftests.py
src/grokimdb/testing.py
src/grokimdb/tests.py
src/grokimdb/app_templates/index.pt
src/grokimdb/locales/grokimdb.pot
src/grokimdb/static/grokimdb.css
