Metadata-Version: 1.0
Name: GrokIMDB
Version: 0.1
Summary: A Grok demo application for editing data retrieved from IMDb.
Home-page: http://cheeseshop.python.org/pypi/GrokIMDB
Author: Uli Fouquet and Jan-Ulrich Hasecke
Author-email: uli@gnufix.de
License: ZPL
Platform: UNKNOWN
Classifier: Development Status :: 3 - Alpha
Classifier: Environment :: Web Environment
Classifier: Intended Audience :: Developers
Classifier: License :: OSI Approved :: Zope Public License
Classifier: Programming Language :: Python
Classifier: Framework :: Zope3
